{
    "Secure Coding": [
        {
            "question": "What is a buffer overflow?1",
            "options": [
                "When a program tries to store more data in a buffer than it can hold", 
                "When a program crashes because of a stack overflow", 
                "When a program's encryption is broken", 
                "When a program's memory usage exceeds a certain limit"],
            "answer": "When a program tries to store more data in a buffer than it can hold",
            "difficulty": "easy"
        },
        {
            "question": "What is the term for an undesirable situation that occurs when a device or system attempts to perform two or more operations at the same time, but because of the nature of the device or system, the operations must be done in the proper sequence to be done correctly?",
            "options": [
                "Buffer overflow", 
                "Race condition", 
                "Multithread application", 
                "Multiple sequence"],
            "answer": "Race condition",
            "difficulty": "medium"
        },
        {
            "question": "What is a buffer overflow?3",
            "options": [
                "When a program tries to store more data in a buffer than it can hold", 
                "When a program crashes because of a stack overflow", 
                "When a program's encryption is broken", 
                "When a program's memory usage exceeds a certain limit"],
            "answer": "When a program tries to store more data in a buffer than it can hold",
            "difficulty": "hard"
        }
    ],
    "Vulnerability Discovery": [
        {
            "question": "What is the term for identifying and prioritizing security issues in real time?",
            "options": ["Vulnerability Discovery", "Vulnerability Identifier", "Real time discovery", "Security analysis"],
            "answer": "Vulnerability Discovery",
            "difficulty": "easy"
        },
        {
            "question": "What is a pro of doing source code review?",
            "options": ["Doesn't require expertise", "Source code is also the production code", "It can be done fast and with full completeness", "Will detect run time issues"],
            "answer": "It can be done fast and with full completeness",
            "difficulty": "medium"
        },
        {
            "question": "Which answer is not one of the four commonly used vulnerability discovery strategy used in software projects?",
            "options": ["Configuration", "Malicious payload construction", "Diagnostics", "Pernicious execution"],
            "answer": "Configuration",
            "difficulty": "hard"
        }
    ],
    "Fuzzing": [
        {
            "question": "What is not a benefit of using fuzzing/fuzz testing?",
            "options": ["It provides a good overall picture of quality of the system", 
                        "Has low overhead for resources", 
                        "Will detect bugs that will not be detected through conventional methods or manual audits", 
                        "Crashes are always easy to analyze"],
            "answer": "Crashes are always easy to analyze",
            "difficulty": "easy"
        },
        {
            "question": "What bug does fuzzing not find?",
            "options": ["Buffer overflow", 
                        "Missing error check", 
                        "Rogue numbers", 
                        "System crashes"],
            "answer": "System crashes",
            "difficulty": "medium"
        },
        {
            "question": "What type of fuzzing does this definition mean: technique used to discover and exploit web applications' vulnerabilities by examining their behavior at run-time without the need for the application's source code?",
            "options": ["Dumb fuzzing", 
                        "Black box fuzzing", 
                        "White box fuzzing", 
                        "Smart fuzzing"],
            "answer": "Black box fuzzing",
            "difficulty": "hard"
        }
    ],
    "Penetration Testing": [
        {
            "question": "What is the difference between a white-box and a black-box penetration test?",
            "options": ["The level of access provided to the tester", "The number of testers involved", "The types of tools used in the test", "The length of the testing period"],
            "answer": "The level of access provided to the tester",
            "difficulty": "easy"
        }
    ],
    "Ethical Hacking": [
        {
            "question": "What is the difference between a hacker and a cracker?",
            "options": ["A hacker is someone who uses their skills for good, while a cracker uses their skills for malicious purposes", "A hacker is someone who breaks into computer systems, while a cracker is someone who breaks into safes", "A hacker is someone who is skilled in programming languages, while a cracker is someone who is skilled in social engineering", "There is no difference"],
            "answer": "A hacker is someone who uses their skills for good, while a cracker uses their skills for malicious purposes",
            "difficulty": "easy"
        }
    ],
    "Exploits/Attacks": [
        {
            "question": "What is a zero-day exploit?",
            "options": ["An exploit that has never been seen before", "An exploit that is highly effective", "An exploit that targets multiple systems at once", "An exploit that is difficult to detect"],
            "answer": "An exploit that has never been seen before",
            "difficulty": "easy"
        }
    ],
    "Countermeasures": [
        {
            "question": "What is a common countermeasure for SQL injection attacks?",
            "options": ["Input validation and sanitization", "Cross-site scripting protection", "Encryption of sensitive data", "Throttling of requests"],
            "answer": "Input validation and sanitization",
            "difficulty": "easy"
        }
    ],
    "Internet Infrastructure": [
        {
            "question": "What is a DDoS attack?",
            "options": ["An attack that involves stealing user data", "An attack that involves brute-forcing login credentials", "An attack that involves overwhelming a system with traffic", "An attack that involves exploiting a vulnerability in a system"],
            "answer": "An attack that involves overwhelming a system with traffic",
            "difficulty": "easy"
        },
        {
            "question": "Which option is not a difference between interdomain routing and intradomain routing?",
            "options": [
                "Interdomain routing wants control over how its traffic is routed while intradomain routing doesn't care",
                "Interdomain routing focuses on policy over performance unlike intradomain routing",
                "Interdomain routing can work within and between domains while intradomain routing only works within domains",
                "Intradomain routing only knows routers within and between their domain while interdomain routing only knows routers within its domain."
                    ],
            "answer": "Intradomain routing only knows routers within and between their domain while interdomain routing only knows routers within its domain.",
            "difficulty": "hard"
        }
    ],
    "Forensic Analysis": [
        {
            "question": "What is the process of extracting digital evidence from volatile memory called?",
            "options": ["Disk imaging", "File carving", "RAM dumping", "Packet capturing"],
            "answer": "RAM dumping",
            "difficulty": "easy"
        }
    ],
    "ML for Cybersecurity": [
        {
            "question": "What type of learning technique is used to train a neural network to detect malware?",
            "options": ["Supervised learning", "Unsupervised learning", "Reinforcement learning", "Deep learning"],
            "answer": "Supervised learning",
            "difficulty": "easy"
        }
    ]
}